tests/__init__.py
tests/test_cary5000.py
tests/test_flow_reactor.py
tests/test_insplorion_light_spectroscopy.py
tests/test_mass_spec.py
tests/test_xps.py
ttlab/__init__.py
ttlab/X0_reactor/X0_functions.py
ttlab/X0_reactor/X0_reactor.py
ttlab/X0_reactor/__init__.py
ttlab/cary5000/__init__.py
ttlab/cary5000/cary5000.py
ttlab/cary5000/cary5000_data_reader.py
ttlab/cary5000/cary5000_functions.py
ttlab/flow_reactor/__init__.py
ttlab/flow_reactor/flow_reactor.py
ttlab/flow_reactor/flow_reactor_date_handler.py
ttlab/flow_reactor/flow_reactor_file_reader.py
ttlab/flow_reactor/flow_reactor_set_and_measured_values_handler.py
ttlab/insplorion_light_spectroscopy/__init__.py
ttlab/insplorion_light_spectroscopy/insplorion_light_spectroscopy.py
ttlab/insplorion_light_spectroscopy/insplorion_light_spectroscopy_file_reader.py
ttlab/insplorion_light_spectroscopy/insplorion_light_spectroscopy_functions.py
ttlab/mass_spectrometer/__init__.py
ttlab/mass_spectrometer/mass_spectrometer.py
ttlab/mass_spectrometer/mass_spectrometer_acquired_data_handler.py
ttlab/mass_spectrometer/mass_spectrometer_date_handler.py
ttlab/mass_spectrometer/mass_spectrometer_file_reader.py
ttlab/xps/XPS.py
ttlab/xps/XPS_data_reader.py
ttlab/xps/XPS_functions.py
ttlab/xps/__init__.py
ttlab-0.43.8.dist-info/DESCRIPTION.rst
ttlab-0.43.8.dist-info/METADATA
ttlab-0.43.8.dist-info/RECORD
ttlab-0.43.8.dist-info/WHEEL
ttlab-0.43.8.dist-info/metadata.json
ttlab-0.43.8.dist-info/top_level.txt
