Metadata-Version: 2.0
Name: ttlab
Version: 0.43.8
Summary: Next generation analysis software
Home-page: UNKNOWN
Author: Christopher Tiburski and Johan Tenghamn
Author-email: info@ttlab.se
License: MIT
Keywords: XPS Cary5000 MassSpec
Platform: UNKNOWN
Classifier: Development Status :: 4 - Beta
Classifier: Programming Language :: Python :: 3.6
Classifier: Intended Audience :: Science/Research
Classifier: Topic :: Scientific/Engineering :: Physics
Requires-Dist: matplotlib
Requires-Dist: scipy
Requires-Dist: numpy
Requires-Dist: plotly
Requires-Dist: astropy
Requires-Dist: pytz
